django_markdown_field/__init__.py
django_markdown_field/apps.py
django_markdown_field/fields.py
django_markdown_field/forms.py
django_markdown_field/widget.py
django_markdown_field/static/admin/js/django_markdown_field/bold-icon.js
django_markdown_field/static/admin/js/django_markdown_field/django-markdown-field.js
django_markdown_field/static/admin/js/django_markdown_field/h1-icon.js
django_markdown_field/static/admin/js/django_markdown_field/h2-icon.js
django_markdown_field/static/admin/js/django_markdown_field/h3-icon.js
django_markdown_field/static/admin/js/django_markdown_field/h4-icon.js
django_markdown_field/static/admin/js/django_markdown_field/h5-icon.js
django_markdown_field/static/admin/js/django_markdown_field/h6-icon.js
django_markdown_field/static/admin/js/django_markdown_field/index.js
django_markdown_field/static/admin/js/django_markdown_field/italic-icon.js
django_markdown_field/static/admin/js/django_markdown_field/link-icon.js
django_markdown_field/static/admin/js/django_markdown_field/list-icon.js
django_markdown_field/static/admin/js/django_markdown_field/list-ordered-icon.js
django_markdown_field/static/admin/js/django_markdown_field/p--7bcw6lo.js
django_markdown_field/static/admin/js/django_markdown_field/p-5v-40HFo.js
django_markdown_field/static/admin/js/django_markdown_field/p-BWDa0A0q.js
django_markdown_field/static/admin/js/django_markdown_field/p-BrWRj1Ah.js
django_markdown_field/static/admin/js/django_markdown_field/p-BwJBiCz-.js
django_markdown_field/static/admin/js/django_markdown_field/p-D5xaqcie.js
django_markdown_field/static/admin/js/django_markdown_field/p-DAXZ5svi.js
django_markdown_field/static/admin/js/django_markdown_field/p-DHnTT7sI.js
django_markdown_field/static/admin/js/django_markdown_field/p-DV3u52r9.js
django_markdown_field/static/admin/js/django_markdown_field/p-DqvYzWfw.js
django_markdown_field/static/admin/js/django_markdown_field/p-FqNvjMPU.js
django_enhanced_markdown_field-0.1.3.dist-info/METADATA
django_enhanced_markdown_field-0.1.3.dist-info/WHEEL
django_enhanced_markdown_field-0.1.3.dist-info/licenses/LICENSE
django_enhanced_markdown_field-0.1.3.dist-info/RECORD
